{
  "filename": "M4 M249 CONOP.pptx",
  "path": "/Users/arpithaprakash/Capstone/3-2CR CONOPs&DRAWs/New folder - Copy (34)/M4 M249 CONOP.pptx",
  "sections": {
    "MISSION": "Killer troop conducts Short Range Marksmanship at Range 101 & 102 on 4-6June24 IOT increase individual soldier lethality.\nTask org: OIC: SSG GGarcia, SSG Reasnover\nNCOIC: SGT Mendoza, SGT Schmanek\nAmmo handler: CPL Cardenas, SGT Ellis\nAlt ammo handler: CPL Hoffman\nTraining PAX: 380 Squadron Troopers\nTime restrictions 24 hours: munitions smaller than 20MM\n0800-2300 munitions 20MM and larger\nTraining Reference:\nTC 3-20.40, Appendix H\nM249Qual\nZERO\nM4Qual\nAmmo point\nAmmo point"
  },
  "source_directory_id": 208,
  "source_directory_name": "New folder - Copy (34)",
  "source_base_directory": "3-2CR CONOPs&DRAWs"
}